study.py
pakagesdist/__init__.py
pakagesdist/tool.py
pakagesdist-1.0.1.dist-info/DESCRIPTION.rst
pakagesdist-1.0.1.dist-info/METADATA
pakagesdist-1.0.1.dist-info/RECORD
pakagesdist-1.0.1.dist-info/WHEEL
pakagesdist-1.0.1.dist-info/metadata.json
pakagesdist-1.0.1.dist-info/top_level.txt
