Metadata-Version: 2.0
Name: pakagesdist
Version: 1.0.1
Summary: this is the first pakage that was created by myself222
Home-page: https://pypi.test.org/simple
Author: clw
Author-email: 2023@qq.com
License: MIT
Platform: UNKNOWN
